jupyterlab_geojson/__init__.py
jupyterlab_geojson/_version.py
jupyterlab_geojson-3.4.0.data/data/share/jupyter/labextensions/@jupyterlab/geojson-extension/package.json
jupyterlab_geojson-3.4.0.data/data/share/jupyter/labextensions/@jupyterlab/geojson-extension/static/00179c4c1ee830d3a108.png
jupyterlab_geojson-3.4.0.data/data/share/jupyter/labextensions/@jupyterlab/geojson-extension/static/066daca850d8ffbef007.png
jupyterlab_geojson-3.4.0.data/data/share/jupyter/labextensions/@jupyterlab/geojson-extension/static/1dbbe9d028e292f36fcb.png
jupyterlab_geojson-3.4.0.data/data/share/jupyter/labextensions/@jupyterlab/geojson-extension/static/264f5c640339f042dd72.png
jupyterlab_geojson-3.4.0.data/data/share/jupyter/labextensions/@jupyterlab/geojson-extension/static/574c3a5cca85f4114085.png
jupyterlab_geojson-3.4.0.data/data/share/jupyter/labextensions/@jupyterlab/geojson-extension/static/62.5e34d4093a41ab340a24.js
jupyterlab_geojson-3.4.0.data/data/share/jupyter/labextensions/@jupyterlab/geojson-extension/static/62.5e34d4093a41ab340a24.js.LICENSE.txt
jupyterlab_geojson-3.4.0.data/data/share/jupyter/labextensions/@jupyterlab/geojson-extension/static/643.bdb928a9116846bf6939.js
jupyterlab_geojson-3.4.0.data/data/share/jupyter/labextensions/@jupyterlab/geojson-extension/static/969.fb561faf72b11e7b2f4e.js
jupyterlab_geojson-3.4.0.data/data/share/jupyter/labextensions/@jupyterlab/geojson-extension/static/remoteEntry.6a76d3e37f02d3977b44.js
jupyterlab_geojson-3.4.0.data/data/share/jupyter/labextensions/@jupyterlab/geojson-extension/static/style.js
jupyterlab_geojson-3.4.0.data/data/share/jupyter/labextensions/@jupyterlab/geojson-extension/static/third-party-licenses.json
jupyterlab_geojson-3.4.0.data/data/share/jupyter/labextensions/@jupyterlab/geojson-extension/install.json
jupyterlab_geojson-3.4.0.dist-info/METADATA
jupyterlab_geojson-3.4.0.dist-info/WHEEL
jupyterlab_geojson-3.4.0.dist-info/licenses/LICENSE
jupyterlab_geojson-3.4.0.dist-info/RECORD
